pyffeditc/__init__.py
pyffeditc/compression.py
pyffeditc/wrapper.py
pyffeditc-0.1.2.dist-info/licenses/LICENSE
tests/__init__.py
tests/test_compression.py
tests/test_wrapper.py
pyffeditc-0.1.2.dist-info/METADATA
pyffeditc-0.1.2.dist-info/WHEEL
pyffeditc-0.1.2.dist-info/top_level.txt
pyffeditc-0.1.2.dist-info/RECORD
