Metadata-Version: 2.4
Name: pyffeditc
Version: 0.1.2
Summary: A Python wrapper for the ffeditc_unicode.exe utility.
Author: Peter Grønbæk Andersen
Author-email: Peter Grønbæk Andersen <peter@grnbk.io>
License: GNU GPL v3
Project-URL: Homepage, https://github.com/pgroenbaek/pyffeditc
Project-URL: Issues, https://github.com/pgroenbaek/pyffeditc/issues
Project-URL: Source, https://github.com/pgroenbaek/pyffeditc
Classifier: Programming Language :: Python :: 3
Classifier: License :: OSI Approved :: GNU General Public License v3 or later (GPLv3+)
Classifier: Operating System :: Microsoft :: Windows
Requires-Python: >=3.6
Requires-Dist: pywin32; sys_platform == "win32"
Dynamic: author
Dynamic: requires-python
